EduTerminal/Edu.py
EduTerminal/_init_.py
EduTerminal-0.7.dist-info/METADATA
EduTerminal-0.7.dist-info/WHEEL
EduTerminal-0.7.dist-info/top_level.txt
EduTerminal-0.7.dist-info/RECORD
