Metadata-Version: 2.1
Name: EduTerminal
Version: 0.7
Summary: Edu tatar library for open-sources projects 
Home-page: UNKNOWN
Author: UNKNOWN
Author-email: alphaste08@gmail.com
License: UNKNOWN
Platform: UNKNOWN
Requires-Dist: requests
Requires-Dist: bs4
Requires-Dist: wheel
